MANIFEST.in
README.rst
setup.py
simple_plus.egg-info/PKG-INFO
simple_plus.egg-info/SOURCES.txt
simple_plus.egg-info/dependency_links.txt
simple_plus.egg-info/not-zip-safe
simple_plus.egg-info/requires.txt
simple_plus.egg-info/top_level.txt
simplepro/.DS_Store
simplepro/.core.so
simplepro/__init__.py
simplepro/action.py
simplepro/apps.py
simplepro/conf.py
simplepro/decorators.py
simplepro/dialog.py
simplepro/filters.py
simplepro/forms.py
simplepro/handlers.py
simplepro/middlewares.py
simplepro/urls.py
simplepro/utils.py
simplepro/__pycache__/__init__.cpython-311.pyc
simplepro/bawa/views.py
simplepro/components/__init__.py
simplepro/components/fields.py
simplepro/components/utils.py
simplepro/components/widgets.py
simplepro/editor/__init__.py
simplepro/editor/fields.py
simplepro/editor/utils.py
simplepro/editor/views.py
simplepro/editor/widgets.py
simplepro/group/utils.py
simplepro/group/view.py
simplepro/locale/zh_Hans/LC_MESSAGES/django.mo
simplepro/locale/zh_Hans/LC_MESSAGES/django.po
simplepro/locale/zh_Hans/LC_MESSAGES/make.sh
simplepro/management/.DS_Store
simplepro/management/commands/active.py
simplepro/management/commands/migrate_menu.py
simplepro/monitor/test.py
simplepro/monitor/utils.py
simplepro/monitor/views.py
simplepro/static/.DS_Store
simplepro/static/admin/.DS_Store
simplepro/static/admin/bawa/BawaData.json
simplepro/static/admin/bawa/demo.html
simplepro/static/admin/bawa/index.html
simplepro/static/admin/bawa/render.common.js
simplepro/static/admin/bawa/render.umd.js
simplepro/static/admin/bawa/render.umd.min.js
simplepro/static/admin/bawa/charts/bar/basic.json
simplepro/static/admin/bawa/charts/bubble/smoking-rate.json
simplepro/static/admin/bawa/charts/bullet/basic.json
simplepro/static/admin/bawa/charts/calendar/basic.json
simplepro/static/admin/bawa/charts/column/basic.json
simplepro/static/admin/bawa/charts/donut/basic.json
simplepro/static/admin/bawa/charts/funnel/basic.json
simplepro/static/admin/bawa/charts/heatmap/basic.json
simplepro/static/admin/bawa/charts/heatmap/jobpaying.json
simplepro/static/admin/bawa/charts/lineplot/basic.json
simplepro/static/admin/bawa/charts/liquid/basic.json
simplepro/static/admin/bawa/charts/pieplot/basic.json
