Metadata-Version: 2.1
Name: simple-plus
Version: 7.0b2
Summary: django admin theme 后台模板
Home-page: https://github.com/newpanjing/simpleui
Author: panjing
Author-email: newpanjing@icloud.com
License: Apache License 2.0
Classifier: Programming Language :: Python :: 3
Classifier: Operating System :: OS Independent
